kitconc/__init__.py
kitconc/core.py
kitconc/export_corpus.py
kitconc/indexing.py
kitconc/kit_app.py
kitconc/kit_app_language.py
kitconc/kit_cmd.py
kitconc/kit_corpus.py
kitconc/kit_data.py
kitconc/kit_models.py
kitconc/kit_plots.py
kitconc/kit_spacy.py
kitconc/kit_tools.py
kitconc/kit_util.py
kitconc/npyarrays.py
kitconc/py_clusters.py
kitconc/py_collocates.py
kitconc/py_concordance.py
kitconc/py_dispersion.py
kitconc/py_keywords.py
kitconc/py_keywords_dispersion.py
kitconc/py_kwic.py
kitconc/py_ngrams.py
kitconc/py_wfreqinfiles.py
kitconc/py_wordlist.py
kitconc/py_wtfreq.py
kitconc/tagged.py
kitconc/tagging.py
kitconc/version.py
kitconc/data/gui_lang.pickle
kitconc/data/gui_lang_default.pickle
kitconc/data/lemmas_english.tab
kitconc/data/pos_tagger_english.pickle
kitconc/data/pos_tagger_portuguese.pickle
kitconc/data/reflist_english.tab
kitconc/data/reflist_no-tagging.tab
kitconc/data/reflist_portuguese.tab
kitconc/data/sent_tokenizer_english.pickle
kitconc/data/sent_tokenizer_portuguese.pickle
kitconc/data/stoplist_english.tab
kitconc/data/stoplist_no-tagging.tab
kitconc/data/stoplist_portuguese.tab
kitconc/data/ubuntu.ttf
kitconc/data/word_tokenizer_english.pickle
kitconc/data/word_tokenizer_portuguese.pickle
kitconc/data/images/excel.png
kitconc/data/images/python.png
kitconc/data/images/python3.ico
kitconc/data/images/python3_b.ico
kitconc/data/images/python_b.png
kitconc/data/images/script.png
kitconc/data/images/text.png
kitconc/data/images/tool.png
kitconc/data/scripts/hello.py
kitconc-3.0.5.dist-info/licenses/LICENSE.txt
kitconc-3.0.5.dist-info/METADATA
kitconc-3.0.5.dist-info/WHEEL
kitconc-3.0.5.dist-info/top_level.txt
kitconc-3.0.5.dist-info/RECORD
