Metadata-Version: 2.4
Name: kitconc
Version: 3.0.5
Summary: A toolkit for Corpus Linguistics Analysis
Home-page: http://pypi.python.org/pypi/Kitconc/
Author: José Lopes Moreira Filho
Author-email: jlopes@alumni.usp.br
License: MIT
License-File: LICENSE.txt
Requires-Dist: numpy<2.0.0,>=1.24.0
Requires-Dist: pandas<3.0.0,>=2.2.0
Requires-Dist: matplotlib<4.0.0,>=3.7.0
Requires-Dist: xlsxwriter<4.0.0,>=3.2.3
Requires-Dist: ttkbootstrap<2.0.0,>=1.12.0
Requires-Dist: pillow<12.0.0,>=11.2.0
Requires-Dist: requests<3.0.0,>=2.31.0
Requires-Dist: nltk<4.0.0,>=3.9.1
Requires-Dist: chardet<6.0.0,>=5.2.0
Requires-Dist: setuptools<70.0.0,>=65.5.0
Dynamic: author
Dynamic: author-email
Dynamic: description
Dynamic: description-content-type
Dynamic: home-page
Dynamic: license
Dynamic: license-file
Dynamic: requires-dist
Dynamic: summary
